[
  {
    "name": "csharp", "label": "C#",
    "items": [
       { "name": "basics", "label": "Basics", "rootpath": "csharp", "filename": "csharp-basics" },
       { "name": "programs", "label": "Programs", "rootpath": "csharp", "filename": "csharp-programs" }
    ]
  },
  {
    "name": "reactjs", "label": "React JS",  "rootpath": "reactjs", 
    "items": [
      { "name": "fundementtals", "label": "Fundementals", "rootpath": "reactjs", "filename": "reactjs-fundementals" },
      { "name": "advanced", "label": "Advanced", "rootpath": "reactjs", "filename": "reactjs-advanced" }
   ]
  },
  {
    "name": "dotnet", "label": ".Net Core", "items": [
      {  "name": "dotnetcore", "label": "Fundementals", "rootpath": "dotnet", "filename": "dotnet-core-fundementals" },
      {  "name": "dotnetcore", "label": "Advanced", "rootpath": "dotnet", "filename": "dotnet-core-advanced" }
    ]
  },
  {
    "name": "microservices", "label": "Microservices", "items": [
      {  "name": "Docker", "label": "Docker", "rootpath": "microservices", "filename": "docker" },
      {  "name": "kubernetes", "label": "Kubernetes", "rootpath": "microservices", "filename": "kubernetes" }
    ]
  },
  {
    "name": "sql", "label": "SQL", "items": [
      {  "name": "sql", "label": "SQL", "rootpath": "sql", "filename": "sql-basics" }
    ]
  },
  {
    "name": "javascript", "label": "JavaScript", "items": [
      { "name": "fundementtals", "label": "Fundementals", "rootpath": "javascript", "filename": "javascript" },
      { "name": "programs", "label": "Programs", "rootpath": "javascript", "filename": "js-programs" }
    ]
  },
  {
    "name": "azure", "label": "Azure", "rootpath": "azure", "filename": "azure"
  }
]